juce_rsa_python/__init__.py
juce_rsa_python-0.0.4.dist-info/LICENSE
juce_rsa_python-0.0.4.dist-info/METADATA
juce_rsa_python-0.0.4.dist-info/WHEEL
juce_rsa_python-0.0.4.dist-info/top_level.txt
juce_rsa_python-0.0.4.dist-info/RECORD
