Metadata-Version: 2.1
Name: juce-rsa-python
Version: 0.0.4
Summary: A juce RSA algorithm implementation without compiling C++ source code
Home-page: https://github.com/xianyuntang/juce-rsa-python
Author: xt1800i
Author-email: xt1800i@example.com
License: UNKNOWN
Platform: UNKNOWN
Classifier: Programming Language :: Python :: 3
Classifier: License :: OSI Approved :: GNU General Public License v3 or later (GPLv3+)
Classifier: Operating System :: OS Independent
License-File: LICENSE
